mojo/networking/__init__.py
mojo/networking/broadcast.py
mojo/networking/constants.py
mojo/networking/exceptions.py
mojo/networking/interfaces.py
mojo/networking/multicast.py
mojo/networking/protocols/__init__.py
mojo/networking/protocols/dns/__init__.py
mojo/networking/protocols/dns/dnsaddress.py
mojo/networking/protocols/dns/dnsapi.py
mojo/networking/protocols/dns/dnsconst.py
mojo/networking/protocols/dns/dnsflags.py
mojo/networking/protocols/dns/dnshostinfo.py
mojo/networking/protocols/dns/dnsinboundmessage.py
mojo/networking/protocols/dns/dnsoutboundmessage.py
mojo/networking/protocols/dns/dnspointer.py
mojo/networking/protocols/dns/dnsquestion.py
mojo/networking/protocols/dns/dnsquestionresults.py
mojo/networking/protocols/dns/dnsrecord.py
mojo/networking/protocols/dns/dnsserver.py
mojo/networking/protocols/dns/dnsservice.py
mojo/networking/protocols/dns/dnstext.py
mojo/networking/protocols/dns/dnsutil.py
mojo/networking/protocols/dns/dnsvalidation.py
mojo/networking/protocols/dns/exceptions.py
mojo/networking/protocols/dns/mdnsbrowser.py
mojo/networking/protocols/dns/mdnsserviceinfo.py
mojo/networking/protocols/dns/testmessages.py
mojo/networking/protocols/ssdp/__init__.py
mojo/networking/protocols/ssdp/ssdppresence.py
mojo/networking/resolution.py
mojo/networking/trafficcapturecontext.py
mojo/networking/unicast.py
mojo_networking-2.0.2.dist-info/LICENSE.txt
mojo_networking-2.0.2.dist-info/METADATA
mojo_networking-2.0.2.dist-info/WHEEL
mojo_networking-2.0.2.dist-info/RECORD
